README.rst
setup.py
robotapi.egg-info/PKG-INFO
robotapi.egg-info/SOURCES.txt
robotapi.egg-info/dependency_links.txt
robotapi.egg-info/requires.txt
robotapi.egg-info/top_level.txt
source/__init__.py
source/roboapi.py
source/serial_connection.py
tests/test_register.py
tests/test_serial.py