Metadata-Version: 1.0
Name: robotapi
Version: 1.0
Summary: Python API for mobile robot control
Home-page: https://github.com/sauravshandilya/SDES-2016-Project2
Author: Parin Chheda, Saurav Shandilya
Author-email: sauravs.iitb@gmail.com
License: BSD
Platform: UNKNOWN
